{"Q6343110":[{"u":"https://live.staticflickr.com/5156/6931549374_c289a14911_b.jpg","o":"Wonderlane","l":"CC BY 2.0","p":"https://www.flickr.com/photos/71401718@N00/6931549374"},{"u":"https://live.staticflickr.com/7106/7059660229_ba5e20d6bb_b.jpg","o":"Wonderlane","l":"CC BY 2.0","p":"https://www.flickr.com/photos/71401718@N00/7059660229"}],"Q7699760":["https://commons.wikimedia.org/wiki/Special:FilePath/Tengboche_Chorten_-_panoramio.jpg","https://commons.wikimedia.org/wiki/Special:FilePath/Tengboche-30-Innenhof-2007-gje.jpg","https://commons.wikimedia.org/wiki/Special:FilePath/Tengboche-32-Innenhof-2007-gje.jpg","https://commons.wikimedia.org/wiki/Special:FilePath/Tengboche-34-innen-2007-gje.jpg","https://commons.wikimedia.org/wiki/Special:FilePath/Tengboche-36-innen-2007-gje.jpg","https://commons.wikimedia.org/wiki/Special:FilePath/Tengboche-38-innen-2007-gje.jpg","https://commons.wikimedia.org/wiki/Special:FilePath/Tengboche-42-innen-2007-gje.jpg","https://commons.wikimedia.org/wiki/Special:FilePath/Tengboche-44-innen-2007-gje.jpg","https://commons.wikimedia.org/wiki/Special:FilePath/Tengboche-54-Innenhof-2007-gje.jpg",{"u":"https://live.staticflickr.com/7136/7704092782_302601029a_b.jpg","o":"Thorsten Hansen","l":"CC BY-ND 2.0","p":"https://www.flickr.com/photos/67850889@N02/7704092782"}],"Q20987851":["https://commons.wikimedia.org/wiki/Special:FilePath/Masjid_Rahmaniya_inside.jpg"],"Q1001415":["https://commons.wikimedia.org/wiki/Special:FilePath/Budhanilkantha-Vishnu-33-Altar-2013-gje.jpg","https://commons.wikimedia.org/wiki/Special:FilePath/Budhanilkantha-Vishnu-34-Altar-2007-gje.jpg","https://commons.wikimedia.org/wiki/Special:FilePath/Budhanilkantha-Vishnu-64-Altar-2013-gje.jpg","https://commons.wikimedia.org/wiki/Special:FilePath/Budhanilkantha-Vishnu-68-Altar-2013-gje.jpg"],"Q1025465":["https://commons.wikimedia.org/wiki/Special:FilePath/Inside_Muktinath_Temple.jpg",{"u":"https://live.staticflickr.com/65535/54893416088_164a4543a5_b.jpg","o":"albategnius","l":"CC BY-SA 4.0","p":"https://www.flickr.com/photos/42914481@N00/54893416088"},{"u":"https://live.staticflickr.com/65535/54893414483_751cdb5e5d_b.jpg","o":"albategnius","l":"CC BY-SA 4.0","p":"https://www.flickr.com/photos/42914481@N00/54893414483"}],"Q106554965":["https://commons.wikimedia.org/wiki/Special:FilePath/Tympanum_of_Balkumari_Temple.jpg"],"Q106808162":["https://commons.wikimedia.org/wiki/Special:FilePath/Devotees_head_inside_the_CG_temple_during_prime_worship_hour.jpg"],"Q108544599":["https://commons.wikimedia.org/wiki/Special:FilePath/Monument_114916.jpg","https://commons.wikimedia.org/wiki/Special:FilePath/Wooden_carved_sculpture_20180918_113835.jpg","https://commons.wikimedia.org/wiki/Special:FilePath/Wooden_carved_sculpture_20180918_113844.jpg","https://commons.wikimedia.org/wiki/Special:FilePath/Wooden_carved_sculpture_20180918_114916.jpg","https://commons.wikimedia.org/wiki/Special:FilePath/Wooden_carved_sculpture_20180918_114923.jpg","https://commons.wikimedia.org/wiki/Special:FilePath/Bisheshor_Mahadev_temple_and_guard_of_Indreshwor.jpg","https://commons.wikimedia.org/wiki/Special:FilePath/Door_of_Indreshwor_mahadev.jpg","https://commons.wikimedia.org/wiki/Special:FilePath/Guard_of_Indreshwor_mahadev.jpg","https://commons.wikimedia.org/wiki/Special:FilePath/Indreswor_Temple_Panauti_IMG_1121_16.jpg","https://commons.wikimedia.org/wiki/Special:FilePath/Indreswor_Temple_Panauti_IMG_1121_17.jpg","https://commons.wikimedia.org/wiki/Special:FilePath/Monument_114155.jpg","https://commons.wikimedia.org/wiki/Special:FilePath/Monument_114203.jpg","https://commons.wikimedia.org/wiki/Special:FilePath/Monument_114216.jpg","https://commons.wikimedia.org/wiki/Special:FilePath/Monument_114223.jpg","https://commons.wikimedia.org/wiki/Special:FilePath/Monument_114233.jpg","https://commons.wikimedia.org/wiki/Special:FilePath/Monument_114244.jpg","https://commons.wikimedia.org/wiki/Special:FilePath/Monument_114259.jpg","https://commons.wikimedia.org/wiki/Special:FilePath/Monument_114312.jpg","https://commons.wikimedia.org/wiki/Special:FilePath/Monument_114319.jpg","https://commons.wikimedia.org/wiki/Special:FilePath/Monument_114338.jpg","https://commons.wikimedia.org/wiki/Special:FilePath/Monument_114347.jpg","https://commons.wikimedia.org/wiki/Special:FilePath/Monument_114359.jpg","https://commons.wikimedia.org/wiki/Special:FilePath/Monument_114416.jpg","https://commons.wikimedia.org/wiki/Special:FilePath/Monument_114730.jpg","https://commons.wikimedia.org/wiki/Special:FilePath/Monument_114733.jpg","https://commons.wikimedia.org/wiki/Special:FilePath/Monument_114737.jpg","https://commons.wikimedia.org/wiki/Special:FilePath/Monument_114741.jpg","https://commons.wikimedia.org/wiki/Special:FilePath/Monument_114745.jpg","https://commons.wikimedia.org/wiki/Special:FilePath/Monument_114748.jpg","https://commons.wikimedia.org/wiki/Special:FilePath/Monument_114803.jpg","https://commons.wikimedia.org/wiki/Special:FilePath/Monument_114908.jpg","https://commons.wikimedia.org/wiki/Special:FilePath/Monument_114944.jpg","https://commons.wikimedia.org/wiki/Special:FilePath/Monument_114958.jpg","https://commons.wikimedia.org/wiki/Special:FilePath/Monument_115003.jpg","https://commons.wikimedia.org/wiki/Special:FilePath/Monument_115013.jpg","https://commons.wikimedia.org/wiki/Special:FilePath/Monument_115017.jpg","https://commons.wikimedia.org/wiki/Special:FilePath/Monument_115024.jpg","https://commons.wikimedia.org/wiki/Special:FilePath/Monument_115039.jpg","https://commons.wikimedia.org/wiki/Special:FilePath/Monument_115046.jpg","https://commons.wikimedia.org/wiki/Special:FilePath/Monument_20180918_113911.jpg","https://commons.wikimedia.org/wiki/Special:FilePath/Monument_20180918_113919.jpg","https://commons.wikimedia.org/wiki/Special:FilePath/Monument_20180918_113927.jpg","https://commons.wikimedia.org/wiki/Special:FilePath/Monument_20180918_113938.jpg","https://commons.wikimedia.org/wiki/Special:FilePath/Monument_20180918_113946.jpg","https://commons.wikimedia.org/wiki/Special:FilePath/Monument_20180918_113954.jpg","https://commons.wikimedia.org/wiki/Special:FilePath/Monument_20180918_114007.jpg","https://commons.wikimedia.org/wiki/Special:FilePath/Monument_20180918_114017.jpg","https://commons.wikimedia.org/wiki/Special:FilePath/Monument_20180918_114025.jpg","https://commons.wikimedia.org/wiki/Special:FilePath/Monument_20180918_114037.jpg","https://commons.wikimedia.org/wiki/Special:FilePath/Monument_20180918_114055.jpg","https://commons.wikimedia.org/wiki/Special:FilePath/Monument_20180918_114105.jpg","https://commons.wikimedia.org/wiki/Special:FilePath/Monument_20180918_114130.jpg","https://commons.wikimedia.org/wiki/Special:FilePath/Monument_20180918_114145.jpg","https://commons.wikimedia.org/wiki/Special:FilePath/Monument_20180918_114328.jpg","https://commons.wikimedia.org/wiki/Special:FilePath/Panauti_Area_2017_128.jpg","https://commons.wikimedia.org/wiki/Special:FilePath/Panauti_Temple_Premises_1021_01.jpg","https://commons.wikimedia.org/wiki/Special:FilePath/Panauti_Temple_Premises_1021_02.jpg","https://commons.wikimedia.org/wiki/Special:FilePath/Panautitemple.jpg","https://commons.wikimedia.org/wiki/Special:FilePath/Shachi_Tirtha_Tribenighat_Panauti-IMG_4350.jpg","https://commons.wikimedia.org/wiki/Special:FilePath/ShachiTirtha_Tribenighat_Panauti-IMG_4278.jpg"],"Q109925262":["https://commons.wikimedia.org/wiki/Special:FilePath/Rishikeshav_inside_Rishikeshav_Temple%2C_Palpa.jpg"],"Q12946982":[{"u":"https://live.staticflickr.com/65535/53323298709_fd8d5b35e0_b.jpg","o":"albategnius","l":"CC BY-SA 2.0","p":"https://www.flickr.com/photos/42914481@N00/53323298709"},"https://commons.wikimedia.org/wiki/Special:FilePath/37479-Kathmandu-Swayambhunath_%285785203017%29.jpg","https://commons.wikimedia.org/wiki/Special:FilePath/Le_Vajra_du_Stupa_de_Swayambhunath_%C3%A0_Katmandou_%288435748930%29.jpg","https://commons.wikimedia.org/wiki/Special:FilePath/Le_grand_Vajra_du_Stupa_de_Swayambhunath_%C3%A0_Katmandou_%288435899936%29.jpg","https://commons.wikimedia.org/wiki/Special:FilePath/Monkey_-_Kathmandu%2C_Nepal_-_panoramio.jpg","https://commons.wikimedia.org/wiki/Special:FilePath/Monkey_Temple_Swayambunath_%2839802374%29.jpeg","https://commons.wikimedia.org/wiki/Special:FilePath/Monkey_at_Swayambhunath_%287476654748%29.jpg","https://commons.wikimedia.org/wiki/Special:FilePath/Monkey_spectating_the_view.jpg","https://commons.wikimedia.org/wiki/Special:FilePath/Monkeys_enjoyment.jpg","https://commons.wikimedia.org/wiki/Special:FilePath/Monkeys_playing_in_shrine_at_Swayambhunath_Stupa_%2816674981244%29.jpg","https://commons.wikimedia.org/wiki/Special:FilePath/Mother%27s_Love_never_fades.jpg","https://commons.wikimedia.org/wiki/Special:FilePath/Potroit_of_Rhesus_Macaque_at_Swayambhunath_Stupa_02.jpg","https://commons.wikimedia.org/wiki/Special:FilePath/Shyanmbunath_Monkey_temple.jpg","https://commons.wikimedia.org/wiki/Special:FilePath/Singe_dans_lenceinte_du_Stupa_de_Swayambhunath_%288435318537%29.jpg","https://commons.wikimedia.org/wiki/Special:FilePath/Singe_dans_lenceinte_du_Stupa_de_Swayambhunath_%288435318727%29.jpg","https://commons.wikimedia.org/wiki/Special:FilePath/Swayambhu_Stupa%2C_Kathmandu%2C_Nepal_%28Unsplash_9ah7Ovj0CDA%29.jpg","https://commons.wikimedia.org/wiki/Special:FilePath/Swayambhunath%2C_Kathmandu%2C_Nepal_%28Unsplash%29.jpg","https://commons.wikimedia.org/wiki/Special:FilePath/Swayambhunath-103.jpg","https://commons.wikimedia.org/wiki/Special:FilePath/Swayambhunath_%2821554135792%29.jpg","https://commons.wikimedia.org/wiki/Special:FilePath/Swayambhunath_%2821554250522%29.jpg","https://commons.wikimedia.org/wiki/Special:FilePath/Swayambhunath_%2821565524065%29.jpg","https://commons.wikimedia.org/wiki/Special:FilePath/Swayambhunath_Premises_2016_104.jpg","https://commons.wikimedia.org/wiki/Special:FilePath/%E5%9B%9B%E7%9C%BC%E5%A4%A9%E7%A5%9E%E5%BB%9F_Harati_Devi_Temple_-_panoramio.jpg","https://commons.wikimedia.org/wiki/Special:FilePath/Les_singes_macaques_rh%C3%A9sus%2C_qui_vivent_autour_du_Stupa_de_Swayambhunath_%C3%A0_Katmandou_45438643935.jpg","https://commons.wikimedia.org/wiki/Special:FilePath/Singe_dans_lenceinte_du_Stupa_de_Swayambhunath_%288435319093%29.jpg","https://commons.wikimedia.org/wiki/Special:FilePath/Singe_dans_lenceinte_du_Stupa_de_Swayambhunath_%288435323149%29.jpg","https://commons.wikimedia.org/wiki/Special:FilePath/Swayambhunath-113.jpg","https://commons.wikimedia.org/wiki/Special:FilePath/Swayambhunath-monkey_on_railing.jpg","https://commons.wikimedia.org/wiki/Special:FilePath/Swayambhunath-monkey_on_stairs.jpg","https://commons.wikimedia.org/wiki/Special:FilePath/Nepal_-_Kathmandu_-_027_-_line_of_chortens_at_Swoyambhunath_%28monkey%29_Temple_%28588298143%29.jpg"],"Q13181210":["https://commons.wikimedia.org/wiki/Special:FilePath/Chobhar-Jal_Binayak-20-Innenhof-2007-gje.jpg"],"Q13183200":["https://commons.wikimedia.org/wiki/Special:FilePath/Pigeon_Flying_Inside_The_Patan_Dhokha.jpg"],"Q18344056":["https://commons.wikimedia.org/wiki/Special:FilePath/Shivalinga_inside_Kumbheshwor_Temple.jpg","https://commons.wikimedia.org/wiki/Special:FilePath/Tympanum_of_Kumbheshwor_Temple.jpg"],"Q19713918":["https://commons.wikimedia.org/wiki/Special:FilePath/Tympanum_of_Supa_Deurali_Temple%2C_Arghakhanchi%2C_Nepal.jpg"],"Q21092001":["https://commons.wikimedia.org/wiki/Special:FilePath/Stone_carved_main_statue_in_the_Rajdevi_Temple_%28Interior_view%29_%281%29.JPG","https://commons.wikimedia.org/wiki/Special:FilePath/Stone_carved_main_statue_in_the_Rajdevi_Temple_%28Interior_view%29_%282%29.JPG","https://commons.wikimedia.org/wiki/Special:FilePath/Stone_carved_main_statue_in_the_Rajdevi_Temple_%28Interior_view%29_%283%29.JPG","https://commons.wikimedia.org/wiki/Special:FilePath/Stone_carved_main_statue_in_the_Rajdevi_Temple_%28Interior_view%29_%284%29.JPG","https://commons.wikimedia.org/wiki/Special:FilePath/Stone_carved_main_statue_in_the_Rajdevi_Temple_%28Interior_view%29_%285%29.JPG"],"Q3161830":["https://commons.wikimedia.org/wiki/Special:FilePath/Historical_Museum_%28Janakpur%29.jpg","https://commons.wikimedia.org/wiki/Special:FilePath/Historical_Museum_2_%28Janakpur%29.jpg","https://commons.wikimedia.org/wiki/Special:FilePath/Historical_Museum_3_%28Janakpur%29.jpg","https://commons.wikimedia.org/wiki/Special:FilePath/Janaki_Mandir%2C_Cultural_Museum.jpg","https://commons.wikimedia.org/wiki/Special:FilePath/Janaki_Teemple_Interior.jpg","https://commons.wikimedia.org/wiki/Special:FilePath/Janaki_Temple_Interior.jpg","https://commons.wikimedia.org/wiki/Special:FilePath/Janakpur_Dham.jpg","https://commons.wikimedia.org/wiki/Special:FilePath/Janakpur_Temple%2C_Nepal_02.jpg","https://commons.wikimedia.org/wiki/Special:FilePath/Janakpur_Temple%2C_Nepal_03.jpg","https://commons.wikimedia.org/wiki/Special:FilePath/Janakpur_Temple%2C_Nepal_04.jpg","https://commons.wikimedia.org/wiki/Special:FilePath/Janakpur_Temple%2C_Nepal_05.jpg","https://commons.wikimedia.org/wiki/Special:FilePath/Janakpur_Temple%2C_Nepal_07.jpg","https://commons.wikimedia.org/wiki/Special:FilePath/Shree_Ramjanaki_Temple_01.jpg","https://commons.wikimedia.org/wiki/Special:FilePath/Statue_of_Goswami_Tulsidas_at_Janaki_Mandir_Historical_Museum_%28Janakpur%29.jpg","https://commons.wikimedia.org/wiki/Special:FilePath/Inside_Janaki_Temple.jpg","https://commons.wikimedia.org/wiki/Special:FilePath/Inside_Janaki_temple.jpg","https://commons.wikimedia.org/wiki/Special:FilePath/Inside_view_of_the_Janki_Mandir_of_Janakpur%2C_Nepal..JPG","https://commons.wikimedia.org/wiki/Special:FilePath/Interior_View_of_Janaki_Temple%2C_Janakpur-September_22%2C_2016-IMG_7448.jpg","https://commons.wikimedia.org/wiki/Special:FilePath/Interior_View_of_Janaki_Temple%2C_Janakpur-September_22%2C_2016-IMG_7449.jpg","https://commons.wikimedia.org/wiki/Special:FilePath/Interior_View_of_Janaki_Temple%2C_Janakpur-September_22%2C_2016-IMG_7450.jpg","https://commons.wikimedia.org/wiki/Special:FilePath/Interior_View_of_Janaki_Temple%2C_Janakpur-September_22%2C_2016-IMG_7451.jpg","https://commons.wikimedia.org/wiki/Special:FilePath/Interior_View_of_Janaki_Temple%2C_Janakpur-September_22%2C_2016-IMG_7452.jpg","https://commons.wikimedia.org/wiki/Special:FilePath/Interior_View_of_Janaki_Temple%2C_Janakpur-September_22%2C_2016-IMG_7453-Pano.jpg","https://commons.wikimedia.org/wiki/Special:FilePath/Interior_View_of_Janaki_Temple%2C_Janakpur-September_22%2C_2016-IMG_7453.jpg","https://commons.wikimedia.org/wiki/Special:FilePath/Interior_View_of_Janaki_Temple%2C_Janakpur-September_22%2C_2016-IMG_7454.jpg","https://commons.wikimedia.org/wiki/Special:FilePath/Interior_View_of_Janaki_Temple%2C_Janakpur-September_22%2C_2016-IMG_7455.jpg","https://commons.wikimedia.org/wiki/Special:FilePath/Interior_View_of_Janaki_Temple%2C_Janakpur-September_22%2C_2016-IMG_7456.jpg","https://commons.wikimedia.org/wiki/Special:FilePath/Interior_View_of_Janaki_Temple%2C_Janakpur-September_22%2C_2016-IMG_7457.jpg","https://commons.wikimedia.org/wiki/Special:FilePath/Interior_View_of_Janaki_Temple%2C_Janakpur-September_22%2C_2016-IMG_7458.jpg","https://commons.wikimedia.org/wiki/Special:FilePath/Interior_View_of_Janaki_Temple%2C_Janakpur-September_22%2C_2016-IMG_7459.jpg","https://commons.wikimedia.org/wiki/Special:FilePath/Interior_View_of_Janaki_Temple%2C_Janakpur-September_22%2C_2016-IMG_7460-Pano.jpg","https://commons.wikimedia.org/wiki/Special:FilePath/Interior_View_of_Janaki_Temple%2C_Janakpur-September_22%2C_2016-IMG_7460.jpg","https://commons.wikimedia.org/wiki/Special:FilePath/Interior_View_of_Janaki_Temple%2C_Janakpur-September_22%2C_2016-IMG_7461.jpg","https://commons.wikimedia.org/wiki/Special:FilePath/Interior_View_of_Janaki_Temple%2C_Janakpur-September_22%2C_2016-IMG_7462.jpg","https://commons.wikimedia.org/wiki/Special:FilePath/Interior_View_of_Janaki_Temple%2C_Janakpur-September_22%2C_2016-IMG_7463.jpg","https://commons.wikimedia.org/wiki/Special:FilePath/Interior_View_of_Janaki_Temple%2C_Janakpur-September_22%2C_2016-IMG_7464.jpg","https://commons.wikimedia.org/wiki/Special:FilePath/Interior_View_of_Janaki_Temple%2C_Janakpur-September_22%2C_2016-IMG_7465.jpg","https://commons.wikimedia.org/wiki/Special:FilePath/Interior_View_of_Janaki_Temple%2C_Janakpur-September_22%2C_2016-IMG_7466.jpg","https://commons.wikimedia.org/wiki/Special:FilePath/Janki_Temple_%28inside_the_temple%29_of_Janakpur_Dham%28Nepal%29.jpg","https://commons.wikimedia.org/wiki/Special:FilePath/Ram_Janaki_Temple_from_inside.jpg","https://commons.wikimedia.org/wiki/Special:FilePath/Upper_view_inside_Janaki_temple.jpg"],"Q380384":["https://commons.wikimedia.org/wiki/Special:FilePath/Basukisthan_Inside_Pashupati_Temple_Pashupatinath_Kathmandu_Nepal_Rajesh_Dhungana_%281%29.jpg","https://commons.wikimedia.org/wiki/Special:FilePath/Basukisthan_Inside_Pashupati_Temple_Pashupatinath_Kathmandu_Nepal_Rajesh_Dhungana_%282%29.jpg","https://commons.wikimedia.org/wiki/Special:FilePath/Basukisthan_Inside_Pashupati_Temple_Pashupatinath_Kathmandu_Nepal_Rajesh_Dhungana_%283%29.jpg","https://commons.wikimedia.org/wiki/Special:FilePath/Pashupatinath-Tempel-07-innen-2007-gje.jpg"],"Q5615319":["https://commons.wikimedia.org/wiki/Special:FilePath/Guhyeshwari_Devi_Murti_inside_Guhyeshwari_Temple%2C_Kathmandu%2C_Nepal.jpg"],"Q5769439":["https://commons.wikimedia.org/wiki/Special:FilePath/Buddha_Statue_at_Hiranya_barna_Mahabihar.jpg","https://commons.wikimedia.org/wiki/Special:FilePath/Hiranyabarna_Mahavihar%2C_Patan_%2818572690582%29.jpg","https://commons.wikimedia.org/wiki/Special:FilePath/Hiranyabarna_Mahavihar%2C_Patan_%2818572700402%29.jpg","https://commons.wikimedia.org/wiki/Special:FilePath/Masked_Gods_at_Golden_Temple_Patan.jpg","https://commons.wikimedia.org/wiki/Special:FilePath/NP_Patan_0906_%2832%29_%2817070814030%29.jpg","https://commons.wikimedia.org/wiki/Special:FilePath/NP_Patan_0906_%2836%29_%2817070812860%29.jpg","https://commons.wikimedia.org/wiki/Special:FilePath/NP_Patan_0906_%2837%29_%2817050950237%29.jpg","https://commons.wikimedia.org/wiki/Special:FilePath/NP_Patan_0906_%2838%29_%2816638149793%29.jpg","https://commons.wikimedia.org/wiki/Special:FilePath/NP_Patan_0906_%2839%29_%2817072145199%29.jpg","https://commons.wikimedia.org/wiki/Special:FilePath/NP_Patan_0906_%2840%29_%2817232381836%29.jpg","https://commons.wikimedia.org/wiki/Special:FilePath/NP_Patan_0906_%2841%29_%2817256590402%29.jpg","https://commons.wikimedia.org/wiki/Special:FilePath/NP_Patan_0906_%2842%29_%2817050948987%29.jpg","https://commons.wikimedia.org/wiki/Special:FilePath/Patan-Buddhist-Monastery-Buddhas_%283011716141%29.jpg","https://commons.wikimedia.org/wiki/Special:FilePath/Patan-Buddhist-Monastery-prayer-room_%283011715697%29.jpg","https://commons.wikimedia.org/wiki/Special:FilePath/Patan-Buddhist-Monastery-prayer-wheels_%283012551758%29.jpg","https://commons.wikimedia.org/wiki/Special:FilePath/Patan-Hiranyabarna_Mahavihar-38-Kloster-2013-gje.jpg","https://commons.wikimedia.org/wiki/Special:FilePath/Star_Goddess_at_Golden_Temple_Patan.jpg","https://commons.wikimedia.org/wiki/Special:FilePath/The_Licchavi_Princess_Bhrikuti_Devi_in_Golden_Temple%2C_Patan.jpg","https://commons.wikimedia.org/wiki/Special:FilePath/Nepal_Patan_Durbar_Square_26_%28full_res%29.jpg","https://commons.wikimedia.org/wiki/Special:FilePath/Vajrasattva_inside_Golden_temple_Patan.jpg"],"Q6374805":["https://commons.wikimedia.org/wiki/Special:FilePath/Architectural_Detail_-_Kasthamandap_Temple_-_Durbar_Square_-_Kathmandu_-_Nepal_-_01_%2813443779695%29.jpg","https://commons.wikimedia.org/wiki/Special:FilePath/Architectural_Detail_-_Kasthamandap_Temple_-_Durbar_Square_-_Kathmandu_-_Nepal_-_02_%2813444137064%29.jpg","https://commons.wikimedia.org/wiki/Special:FilePath/Basantapur_Kathmandu_Nepal_%288528311443%29.jpg","https://commons.wikimedia.org/wiki/Special:FilePath/Basantapur_Kathmandu_Nepal_%288528314145%29.jpg","https://commons.wikimedia.org/wiki/Special:FilePath/Kasthamandap_%287007264622%29.jpg","https://commons.wikimedia.org/wiki/Special:FilePath/Kasthamandap_temple%2C_Kathmandu%2C_Nepal_%2823824729444%29.jpg","https://commons.wikimedia.org/wiki/Special:FilePath/Kasthamandap_temple%2C_Kathmandu%2C_Nepal_%2824085129729%29.jpg","https://commons.wikimedia.org/wiki/Special:FilePath/Kasthamandap_%E2%80%93_Kathmandu_-_01.jpg","https://commons.wikimedia.org/wiki/Special:FilePath/Kathmandu-Kasthamandap-14-innen-2013-gje.jpg","https://commons.wikimedia.org/wiki/Special:FilePath/Kathmandu-Kasthamandap-16-innen-2013-gje.jpg","https://commons.wikimedia.org/wiki/Special:FilePath/Nepal_-15_%2815592818539%29.jpg","https://commons.wikimedia.org/wiki/Special:FilePath/Autel_d%C3%A9di%C3%A9_%C3%A0_Ganesh_%28Katmandou%29_%288574766106%29.jpg","https://commons.wikimedia.org/wiki/Special:FilePath/Durbar-Square-Kathmandu_%283015700835%29.jpg","https://commons.wikimedia.org/wiki/Special:FilePath/Durbar-Square-Kathmandu_%283016536106%29.jpg","https://commons.wikimedia.org/wiki/Special:FilePath/Durbar-Square-Kathmandu_%283016536720%29.jpg","https://commons.wikimedia.org/wiki/Special:FilePath/Ganesha_Shrine%2C_Kasthamandap%2C_Kathmandu%2C_Nepal_%2824426707886%29.jpg","https://commons.wikimedia.org/wiki/Special:FilePath/Ganesha_Shrine%2C_Kasthamandap%2C_Kathmandu%2C_Nepal_%28315373341%29.jpg"],"Q83776242":["https://commons.wikimedia.org/wiki/Special:FilePath/Rare_Picture_of_Toran_Inside_Taleju_Bhawani_temple%2C_only_hindus_are_allowed_to_enter_temple.jpg"],"Q85746836":["https://commons.wikimedia.org/wiki/Special:FilePath/Bhadrakali_Inside_Area_01.jpg","https://commons.wikimedia.org/wiki/Special:FilePath/Bhadrakali_Inside_Area_02.jpg","https://commons.wikimedia.org/wiki/Special:FilePath/Bhadrakali_Inside_Area_03.jpg","https://commons.wikimedia.org/wiki/Special:FilePath/Bhadrakali_Inside_Area_04.jpg","https://commons.wikimedia.org/wiki/Special:FilePath/Bhadrakali_Inside_Area_05.jpg","https://commons.wikimedia.org/wiki/Special:FilePath/Bhadrakali_Inside_Area_06.jpg","https://commons.wikimedia.org/wiki/Special:FilePath/Bhadrakali_Inside_Area_07.jpg","https://commons.wikimedia.org/wiki/Special:FilePath/Bhadrakali_Inside_Area_08.jpg","https://commons.wikimedia.org/wiki/Special:FilePath/Bhadrakali_Inside_Area_09.jpg","https://commons.wikimedia.org/wiki/Special:FilePath/Bhadrakali_Inside_Area_10.jpg","https://commons.wikimedia.org/wiki/Special:FilePath/Bhadrakali_Inside_Area_11.jpg","https://commons.wikimedia.org/wiki/Special:FilePath/Bhadrakali_Inside_Area_12.jpg","https://commons.wikimedia.org/wiki/Special:FilePath/Bhadrakali_Inside_Area_13.jpg","https://commons.wikimedia.org/wiki/Special:FilePath/Bhadrakali_Inside_Area_14.jpg","https://commons.wikimedia.org/wiki/Special:FilePath/Bhadrakali_Inside_Area_15.jpg","https://commons.wikimedia.org/wiki/Special:FilePath/Bhadrakali_Inside_Area_16.jpg","https://commons.wikimedia.org/wiki/Special:FilePath/Bhadrakali_Inside_Area_17.jpg","https://commons.wikimedia.org/wiki/Special:FilePath/Bhadrakali_Inside_Area_18.jpg","https://commons.wikimedia.org/wiki/Special:FilePath/Bhadrakali_Inside_Area_19.jpg","https://commons.wikimedia.org/wiki/Special:FilePath/Bhadrakali_Inside_Area_20.jpg","https://commons.wikimedia.org/wiki/Special:FilePath/Bhadrakali_Inside_Area_21.jpg"],"Q97357162":["https://commons.wikimedia.org/wiki/Special:FilePath/Ganesh_Mandhir_inside_Bhadrakali_area.jpg","https://commons.wikimedia.org/wiki/Special:FilePath/Kuti_inside_Bhadrakali_template_area.jpg"],"Q4700324":["https://commons.wikimedia.org/wiki/Special:FilePath/Idols_inside_Aakash_Bhairav_Temple.jpg"],"Q83696529":["https://commons.wikimedia.org/wiki/Special:FilePath/Annapurna_Mai_Statue_inside_Mandir_%281%29.jpg","https://commons.wikimedia.org/wiki/Special:FilePath/Annapurna_Mai_Statue_inside_Mandir_%282%29.jpg","https://commons.wikimedia.org/wiki/Special:FilePath/Annapurna_Mai_Statue_inside_Mandir.jpg"],"Q83704903":["https://commons.wikimedia.org/wiki/Special:FilePath/Carvings_in_the_ceiling_beams_of_The_Jagannath_temple.jpg","https://commons.wikimedia.org/wiki/Special:FilePath/Jagannath_Temple_in_which_image_of_Jagannath_situated_inside_dates_back_to_1563.jpg"],"Q13357831":["https://commons.wikimedia.org/wiki/Special:FilePath/Holy_Pond_inside_the_Kalinchwok_Temple.jpg","https://commons.wikimedia.org/wiki/Special:FilePath/The_main_temple_at_Kalinchwok%2C_the_holy_pond_is_inside.jpg"],"Q106514630":["https://commons.wikimedia.org/wiki/Special:FilePath/Full_length_mirror_giving_a_view_into_the_inner_sanctum_of_Mahabuddha_Temple.jpeg"],"Q138701570":["https://commons.wikimedia.org/wiki/Special:FilePath/017_Dawn_over_Stupa%2C_Kapilavastu_%289237259001%29.jpg","https://commons.wikimedia.org/wiki/Special:FilePath/018_Circumambulating_Stupa%2C_Kapilavastu_%289237250723%29.jpg","https://commons.wikimedia.org/wiki/Special:FilePath/019_Worshipping_the_Stupa%2C_Kapilavastu_%289240021702%29.jpg","https://commons.wikimedia.org/wiki/Special:FilePath/Kapilavastu_Stupas-Original-00020.jpg","https://commons.wikimedia.org/wiki/Special:FilePath/Nepal_-_Excavations%2C_Kapilavastu_%289239993896%29.jpg","https://commons.wikimedia.org/wiki/Special:FilePath/Nepal_-_Stupa%2C_Kapilavastu_%289240004790%29.jpg","https://commons.wikimedia.org/wiki/Special:FilePath/Nepal_-_Walls_and_Building%2C_Kapilavastu_%289239983376%29.jpg","https://commons.wikimedia.org/wiki/Special:FilePath/North-East_View_Of_Salya_Stupa.jpg","https://commons.wikimedia.org/wiki/Special:FilePath/North-East_View_Of_Salya_Stupa_%282%29.jpg","https://commons.wikimedia.org/wiki/Special:FilePath/Piprahwa_Stupa_Kapilvastu.jpg","https://commons.wikimedia.org/wiki/Special:FilePath/Salya_Stupa_%282%29.jpg","https://commons.wikimedia.org/wiki/Special:FilePath/Salya_Stupa.jpg","https://commons.wikimedia.org/wiki/Special:FilePath/Stupas-Original-00021.jpg","https://commons.wikimedia.org/wiki/Special:FilePath/The_Piprahwa_Stupa.png","https://commons.wikimedia.org/wiki/Special:FilePath/View_of_Salya_Stupa_from_Lotus_Pond.jpg","https://commons.wikimedia.org/wiki/Special:FilePath/View_of_Salya_Stupa_from_Lotus_Pond_%282%29.jpg","https://commons.wikimedia.org/wiki/Special:FilePath/View_of_Salya_Stupa_from_Lotus_Pond_%283%29.jpg","https://commons.wikimedia.org/wiki/Special:FilePath/View_of_Salya_Stupa_from_North_%282%29.jpg","https://commons.wikimedia.org/wiki/Special:FilePath/View_of_Salya_Stupa_from_West.jpg","https://commons.wikimedia.org/wiki/Special:FilePath/View_of_Salya_stupa_from_North.jpg","https://commons.wikimedia.org/wiki/Special:FilePath/View_of_Salya_stupa_from_North_%283%29.jpg","https://commons.wikimedia.org/wiki/Special:FilePath/View_of_Stupa_from_South.jpg","https://commons.wikimedia.org/wiki/Special:FilePath/View_of_Stupa_from_South_%283%29.jpg"],"Q7698769":["https://commons.wikimedia.org/wiki/Special:FilePath/Swayambhunath-144.jpg"],"Q1059208":["https://commons.wikimedia.org/wiki/Special:FilePath/A_groundplan_from_1811_%28copper_engraving%29.jpg","https://commons.wikimedia.org/wiki/Special:FilePath/Ajanta_Caves%2C_India%2C_Interior_of_Ajanta_chaitya_%28stupa%29_worship_hall%2C_Cave_26.jpg","https://commons.wikimedia.org/wiki/Special:FilePath/Ajanta_Caves%2C_India%2C_Interior_of_Ajanta_stupa_worship_hall.jpg","https://commons.wikimedia.org/wiki/Special:FilePath/Henry_Salt_-_Ground_plan_of_Carli_Cave.jpg"],"c4:nm:1593 church monuments":["https://commons.wikimedia.org/wiki/Special:FilePath/Appleton_StLawrence_Monument_JohnFettiplace.JPG","https://commons.wikimedia.org/wiki/Special:FilePath/Appleton_StLawrence_Monument_JohnFettiplace_Complete.JPG"],"c4:nm:1722 church monuments":["https://commons.wikimedia.org/wiki/Special:FilePath/Piddington_StNicholas_Chancel_NorthEast.JPG"],"c4:nm:1710 church monuments":["https://commons.wikimedia.org/wiki/Special:FilePath/Piddington_StNicholas_Chancel_NorthWest.JPG"],"c4:nm:church monuments":["https://commons.wikimedia.org/wiki/Special:FilePath/At_Marlborough_2023_037.jpg","https://commons.wikimedia.org/wiki/Special:FilePath/At_Marlborough_2023_038.jpg","https://commons.wikimedia.org/wiki/Special:FilePath/At_Marlborough_2023_045.jpg","https://commons.wikimedia.org/wiki/Special:FilePath/At_Marlborough_2023_046.jpg","https://commons.wikimedia.org/wiki/Special:FilePath/At_Marlborough_2023_047.jpg","https://commons.wikimedia.org/wiki/Special:FilePath/At_Marlborough_2023_052.jpg","https://commons.wikimedia.org/wiki/Special:FilePath/At_Marlborough_2023_055.jpg","https://commons.wikimedia.org/wiki/Special:FilePath/At_Marlborough_2023_056.jpg","https://commons.wikimedia.org/wiki/Special:FilePath/John_Everett_Millais_-_L%27Enfant_du_Regiment_-_Google_Art_Project.jpg","https://commons.wikimedia.org/wiki/Special:FilePath/Papirnata_slika_BDM_crkva_Gospe_Trsatske_010708.jpg","https://commons.wikimedia.org/wiki/Special:FilePath/Pero_Carneiro.JPG","https://commons.wikimedia.org/wiki/Special:FilePath/Salawa1.JPG","https://commons.wikimedia.org/wiki/Special:FilePath/Salawa2.JPG","https://commons.wikimedia.org/wiki/Special:FilePath/Sepulcro_de_los_D%C3%ADez_Ortega.jpg","https://commons.wikimedia.org/wiki/Special:FilePath/Sir_Thomas_Hanmer%27s_monument%2C_Hanmer_Chapel%2C_1794.jpg"],"c4:nm:1878 church monuments":["https://commons.wikimedia.org/wiki/Special:FilePath/Monument_to_Mary_Carpenter_-_Bristol_Cathedral_-_DSC_0737.jpg"],"c4:nm:1906 church monuments":["https://commons.wikimedia.org/wiki/Special:FilePath/Salisbury_03.jpg"],"c4:Um\u0101mahe\u015bvara Mandira at C\u0101ka B\u0101h\u0101\u1e25 [170a68d0]":[{"u":"https://danam.cats.uni-heidelberg.de/files/uploadedfiles/LAL2750_I_20190209_09.jpg","o":"Yogesh Budathoki","l":"CC BY-SA 4.0 (NHDP)","p":"https://danam.cats.uni-heidelberg.de/files/uploadedfiles/LAL2750_I_20190209_09.jpg"},{"u":"https://danam.cats.uni-heidelberg.de/files/uploadedfiles/LAL2750_I_20190209_12.jpg","o":"Yogesh Budathoki","l":"CC BY-SA 4.0 (NHDP)","p":"https://danam.cats.uni-heidelberg.de/files/uploadedfiles/LAL2750_I_20190209_12.jpg"},{"u":"https://danam.cats.uni-heidelberg.de/files/uploadedfiles/LAL2750_P_20190209_06_poCZETK.jpg","o":"Yogesh Budathoki","l":"CC BY-SA 4.0 (NHDP)","p":"https://danam.cats.uni-heidelberg.de/files/uploadedfiles/LAL2750_P_20190209_06_poCZETK.jpg"},{"u":"https://danam.cats.uni-heidelberg.de/files/uploadedfiles/LAL2750_I_20190209_06.jpg","o":"Yogesh Budathoki","l":"CC BY-SA 4.0 (NHDP)","p":"https://danam.cats.uni-heidelberg.de/files/uploadedfiles/LAL2750_I_20190209_06.jpg"},{"u":"https://danam.cats.uni-heidelberg.de/files/uploadedfiles/LAL2750_I_20190209_07.jpg","o":"Yogesh Budathoki","l":"CC BY-SA 4.0 (NHDP)","p":"https://danam.cats.uni-heidelberg.de/files/uploadedfiles/LAL2750_I_20190209_07.jpg"},{"u":"https://danam.cats.uni-heidelberg.de/files/uploadedfiles/LAL2750_I_20190209_08.jpg","o":"Yogesh Budathoki","l":"CC BY-SA 4.0 (NHDP)","p":"https://danam.cats.uni-heidelberg.de/files/uploadedfiles/LAL2750_I_20190209_08.jpg"},{"u":"https://danam.cats.uni-heidelberg.de/files/uploadedfiles/LAL2750_I_20190209_03.jpg","o":"Yogesh Budathoki","l":"CC BY-SA 4.0 (NHDP)","p":"https://danam.cats.uni-heidelberg.de/files/uploadedfiles/LAL2750_I_20190209_03.jpg"},{"u":"https://danam.cats.uni-heidelberg.de/files/uploadedfiles/LAL2750_I_20190209_04.jpg","o":"Yogesh Budathoki","l":"CC BY-SA 4.0 (NHDP)","p":"https://danam.cats.uni-heidelberg.de/files/uploadedfiles/LAL2750_I_20190209_04.jpg"},{"u":"https://danam.cats.uni-heidelberg.de/files/uploadedfiles/LAL2750_I_20190209_05.jpg","o":"Yogesh Budathoki","l":"CC BY-SA 4.0 (NHDP)","p":"https://danam.cats.uni-heidelberg.de/files/uploadedfiles/LAL2750_I_20190209_05.jpg"},{"u":"https://danam.cats.uni-heidelberg.de/files/uploadedfiles/LAL2750_I_20190209_21.jpg","o":"Yogesh Budathoki","l":"CC BY-SA 4.0 (NHDP)","p":"https://danam.cats.uni-heidelberg.de/files/uploadedfiles/LAL2750_I_20190209_21.jpg"},{"u":"https://danam.cats.uni-heidelberg.de/files/uploadedfiles/LAL2750_I_20190209_11_3JTpnop.jpg","o":"Yogesh Budathoki","l":"CC BY-SA 4.0 (NHDP)","p":"https://danam.cats.uni-heidelberg.de/files/uploadedfiles/LAL2750_I_20190209_11_3JTpnop.jpg"},{"u":"https://danam.cats.uni-heidelberg.de/files/uploadedfiles/LAL2750_I_20190209_10_ZbW5eT9.jpg","o":"Yogesh Budathoki","l":"CC BY-SA 4.0 (NHDP)","p":"https://danam.cats.uni-heidelberg.de/files/uploadedfiles/LAL2750_I_20190209_10_ZbW5eT9.jpg"},{"u":"https://danam.cats.uni-heidelberg.de/files/uploadedfiles/LAL2750_I_20190209_13.jpg","o":"Yogesh Budathoki","l":"CC BY-SA 4.0 (NHDP)","p":"https://danam.cats.uni-heidelberg.de/files/uploadedfiles/LAL2750_I_20190209_13.jpg"},{"u":"https://danam.cats.uni-heidelberg.de/files/uploadedfiles/LAL2750_I_20190209_10_3hPd0mo.jpg","o":"Yogesh Budathoki","l":"CC BY-SA 4.0 (NHDP)","p":"https://danam.cats.uni-heidelberg.de/files/uploadedfiles/LAL2750_I_20190209_10_3hPd0mo.jpg"},{"u":"https://danam.cats.uni-heidelberg.de/files/uploadedfiles/LAL2750_I_20190209_10_A2lnf7Y.jpg","o":"Yogesh Budathoki","l":"CC BY-SA 4.0 (NHDP)","p":"https://danam.cats.uni-heidelberg.de/files/uploadedfiles/LAL2750_I_20190209_10_A2lnf7Y.jpg"},{"u":"https://danam.cats.uni-heidelberg.de/files/uploadedfiles/LAL2750_I_20190209_01.jpg","o":"Yogesh Budathoki","l":"CC BY-SA 4.0 (NHDP)","p":"https://danam.cats.uni-heidelberg.de/files/uploadedfiles/LAL2750_I_20190209_01.jpg"},{"u":"https://danam.cats.uni-heidelberg.de/files/uploadedfiles/LAL2750_I_20190209_02.jpg","o":"Yogesh Budathoki","l":"CC BY-SA 4.0 (NHDP)","p":"https://danam.cats.uni-heidelberg.de/files/uploadedfiles/LAL2750_I_20190209_02.jpg"},{"u":"https://danam.cats.uni-heidelberg.de/files/uploadedfiles/LAL2750_P_20190209_07_HRzKtpz.jpg","o":"Yogesh Budathoki","l":"CC BY-SA 4.0 (NHDP)","p":"https://danam.cats.uni-heidelberg.de/files/uploadedfiles/LAL2750_P_20190209_07_HRzKtpz.jpg"},{"u":"https://danam.cats.uni-heidelberg.de/files/uploadedfiles/LAL2750_P_20190209_01.jpg","o":"NHDP","l":"CC BY-SA 4.0 (NHDP)","p":"https://danam.cats.uni-heidelberg.de/files/uploadedfiles/LAL2750_P_20190209_01.jpg"}],"c4:Dharmadha\u0304tujina\u0304laya Caitya (1962 CE) [e0a00834]":[{"u":"https://danam.cats.uni-heidelberg.de/files/uploadedfiles/BUN0014_I_20200213_01.JPG","o":"Thomas Schrom","l":"CC BY-SA 4.0 (NHDP)","p":"https://danam.cats.uni-heidelberg.de/files/uploadedfiles/BUN0014_I_20200213_01.JPG"},{"u":"https://danam.cats.uni-heidelberg.de/files/uploadedfiles/BUN0014_I_20200202_01.jpg","o":"Thomas Schrom","l":"CC BY-SA 4.0 (NHDP)","p":"https://danam.cats.uni-heidelberg.de/files/uploadedfiles/BUN0014_I_20200202_01.jpg"},{"u":"https://danam.cats.uni-heidelberg.de/files/uploadedfiles/BUN0014_I_20200213_02.JPG","o":"Thomas Schrom","l":"CC BY-SA 4.0 (NHDP)","p":"https://danam.cats.uni-heidelberg.de/files/uploadedfiles/BUN0014_I_20200213_02.JPG"},{"u":"https://danam.cats.uni-heidelberg.de/files/uploadedfiles/BUN0014_I_20200202_02.jpg","o":"Thomas Schrom","l":"CC BY-SA 4.0 (NHDP)","p":"https://danam.cats.uni-heidelberg.de/files/uploadedfiles/BUN0014_I_20200202_02.jpg"},{"u":"https://danam.cats.uni-heidelberg.de/files/uploadedfiles/BUN0014_P_20191213.JPG","o":"NHDP","l":"CC BY-SA 4.0 (NHDP)","p":"https://danam.cats.uni-heidelberg.de/files/uploadedfiles/BUN0014_P_20191213.JPG"}],"c4:Iku B\u0101h\u0101\u1e25 [dd8ad654]":[{"u":"https://danam.cats.uni-heidelberg.de/files/uploadedfiles/LAL0130_P_20181031_08.jpg","o":"NHDP","l":"CC BY-SA 4.0 (NHDP)","p":"https://danam.cats.uni-heidelberg.de/files/uploadedfiles/LAL0130_P_20181031_08.jpg"},{"u":"https://danam.cats.uni-heidelberg.de/files/e63924c6-e6c2-11ea-8bb9-0242ac120007","o":"NHDP","l":"CC BY-SA 4.0 (NHDP)","p":"https://danam.cats.uni-heidelberg.de/files/e63924c6-e6c2-11ea-8bb9-0242ac120007"},{"u":"https://danam.cats.uni-heidelberg.de/files/3059f820-e6c1-11ea-a0c3-0242ac120007","o":"NHDP","l":"CC BY-SA 4.0 (NHDP)","p":"https://danam.cats.uni-heidelberg.de/files/3059f820-e6c1-11ea-a0c3-0242ac120007"},{"u":"https://danam.cats.uni-heidelberg.de/files/de3c3426-e6c1-11ea-a0c3-0242ac120007","o":"NHDP","l":"CC BY-SA 4.0 (NHDP)","p":"https://danam.cats.uni-heidelberg.de/files/de3c3426-e6c1-11ea-a0c3-0242ac120007"},{"u":"https://danam.cats.uni-heidelberg.de/files/uploadedfiles/LAL0130_P_20181031_01.jpg","o":"NHDP","l":"CC BY-SA 4.0 (NHDP)","p":"https://danam.cats.uni-heidelberg.de/files/uploadedfiles/LAL0130_P_20181031_01.jpg"}],"c4:Dharmadha\u0304tu Man\u0323d\u0323ala (1964 CE) [2507d356]":[{"u":"https://danam.cats.uni-heidelberg.de/files/uploadedfiles/BUN0015_I_20200202.jpg","o":"NHDP","l":"CC BY-SA 4.0 (NHDP)","p":"https://danam.cats.uni-heidelberg.de/files/uploadedfiles/BUN0015_I_20200202.jpg"}],"c4:Bh\u012bmar\u0101ja B\u0101h\u0101\u1e25 (1909 CE) [794a1040]":[{"u":"https://danam.cats.uni-heidelberg.de/files/uploadedfiles/LAL2360_P_20190509_03.jpg","o":"NHDP","l":"CC BY-SA 4.0 (NHDP)","p":"https://danam.cats.uni-heidelberg.de/files/uploadedfiles/LAL2360_P_20190509_03.jpg"},{"u":"https://danam.cats.uni-heidelberg.de/files/uploadedfiles/LAL2360_P_20190509_14.jpg","o":"NHDP","l":"CC BY-SA 4.0 (NHDP)","p":"https://danam.cats.uni-heidelberg.de/files/uploadedfiles/LAL2360_P_20190509_14.jpg"}],"c4:Devajyoti B\u0101h\u0101\u1e25 (1889 CE) [26e27d10]":[{"u":"https://danam.cats.uni-heidelberg.de/files/uploadedfiles/LAL0451_P_20191003_01.jpg","o":"NHDP","l":"CC BY-SA 4.0 (NHDP)","p":"https://danam.cats.uni-heidelberg.de/files/uploadedfiles/LAL0451_P_20191003_01.jpg"},{"u":"https://danam.cats.uni-heidelberg.de/files/uploadedfiles/LAL0451_P_20191003_07.jpg","o":"NHDP","l":"CC BY-SA 4.0 (NHDP)","p":"https://danam.cats.uni-heidelberg.de/files/uploadedfiles/LAL0451_P_20191003_07.jpg"},{"u":"https://danam.cats.uni-heidelberg.de/files/uploadedfiles/LAL0451_I_20191003_01_vApl3Mf.JPG","o":"NHDP","l":"CC BY-SA 4.0 (NHDP)","p":"https://danam.cats.uni-heidelberg.de/files/uploadedfiles/LAL0451_I_20191003_01_vApl3Mf.JPG"},{"u":"https://danam.cats.uni-heidelberg.de/files/uploadedfiles/LAL0451_P_20191003_02.jpg","o":"NHDP","l":"CC BY-SA 4.0 (NHDP)","p":"https://danam.cats.uni-heidelberg.de/files/uploadedfiles/LAL0451_P_20191003_02.jpg"}],"c4:Dune B\u0101h\u0101\u1e25 [e273afc4]":[{"u":"https://danam.cats.uni-heidelberg.de/files/uploadedfiles/LAL0700_P_20200303_08.jpg","o":"Nashib Kafle","l":"CC BY-SA 4.0 (NHDP)","p":"https://danam.cats.uni-heidelberg.de/files/uploadedfiles/LAL0700_P_20200303_08.jpg"},{"u":"https://danam.cats.uni-heidelberg.de/files/uploadedfiles/LAL0700_P_20200303_01.jpg","o":"NHDP","l":"CC BY-SA 4.0 (NHDP)","p":"https://danam.cats.uni-heidelberg.de/files/uploadedfiles/LAL0700_P_20200303_01.jpg"}],"c4:Maha\u0304ka\u0304la Shrine (ca. early 20th cent. CE) [5a2b953a]":[{"u":"https://danam.cats.uni-heidelberg.de/files/uploadedfiles/SUN0200-002_I_20191104_02_NVcKqOZ.jpg","o":"NHDP","l":"CC BY-SA 4.0 (NHDP)","p":"https://danam.cats.uni-heidelberg.de/files/uploadedfiles/SUN0200-002_I_20191104_02_NVcKqOZ.jpg"},{"u":"https://danam.cats.uni-heidelberg.de/files/uploadedfiles/SUN0200-003_I_20191104_01.jpg","o":"NHDP","l":"CC BY-SA 4.0 (NHDP)","p":"https://danam.cats.uni-heidelberg.de/files/uploadedfiles/SUN0200-003_I_20191104_01.jpg"},{"u":"https://danam.cats.uni-heidelberg.de/files/uploadedfiles/SUN0200_I_20191104_01.jpg","o":"NHDP","l":"CC BY-SA 4.0 (NHDP)","p":"https://danam.cats.uni-heidelberg.de/files/uploadedfiles/SUN0200_I_20191104_01.jpg"},{"u":"https://danam.cats.uni-heidelberg.de/files/uploadedfiles/SUN0200_P_20191017_03.jpg","o":"NHDP","l":"CC BY-SA 4.0 (NHDP)","p":"https://danam.cats.uni-heidelberg.de/files/uploadedfiles/SUN0200_P_20191017_03.jpg"},{"u":"https://danam.cats.uni-heidelberg.de/files/uploadedfiles/SUN0200_P_20191017_10.jpg","o":"NHDP","l":"CC BY-SA 4.0 (NHDP)","p":"https://danam.cats.uni-heidelberg.de/files/uploadedfiles/SUN0200_P_20191017_10.jpg"},{"u":"https://danam.cats.uni-heidelberg.de/files/uploadedfiles/SUN0200-002_I_20191104_01.jpg","o":"NHDP","l":"CC BY-SA 4.0 (NHDP)","p":"https://danam.cats.uni-heidelberg.de/files/uploadedfiles/SUN0200-002_I_20191104_01.jpg"},{"u":"https://danam.cats.uni-heidelberg.de/files/uploadedfiles/SUN0200-003_I_20191104_02_SAQNnyv.jpg","o":"NHDP","l":"CC BY-SA 4.0 (NHDP)","p":"https://danam.cats.uni-heidelberg.de/files/uploadedfiles/SUN0200-003_I_20191104_02_SAQNnyv.jpg"},{"u":"https://danam.cats.uni-heidelberg.de/files/uploadedfiles/SUN0200_D_2019_location_map_rQVGFTB.png","o":"NHDP","l":"CC BY-SA 4.0 (NHDP)","p":"https://danam.cats.uni-heidelberg.de/files/uploadedfiles/SUN0200_D_2019_location_map_rQVGFTB.png"},{"u":"https://danam.cats.uni-heidelberg.de/files/uploadedfiles/SUN0200_P_20191017_01.jpg","o":"NHDP","l":"CC BY-SA 4.0 (NHDP)","p":"https://danam.cats.uni-heidelberg.de/files/uploadedfiles/SUN0200_P_20191017_01.jpg"},{"u":"https://danam.cats.uni-heidelberg.de/files/uploadedfiles/SUN0200_P_20191017_02.jpg","o":"NHDP","l":"CC BY-SA 4.0 (NHDP)","p":"https://danam.cats.uni-heidelberg.de/files/uploadedfiles/SUN0200_P_20191017_02.jpg"},{"u":"https://danam.cats.uni-heidelberg.de/files/uploadedfiles/SUN0200_P_20191104_01.jpg","o":"NHDP","l":"CC BY-SA 4.0 (NHDP)","p":"https://danam.cats.uni-heidelberg.de/files/uploadedfiles/SUN0200_P_20191104_01.jpg"},{"u":"https://danam.cats.uni-heidelberg.de/files/uploadedfiles/SUN0200_D_2019_floor_plan_and_elevations.png","o":"NHDP","l":"CC BY-SA 4.0 (NHDP)","p":"https://danam.cats.uni-heidelberg.de/files/uploadedfiles/SUN0200_D_2019_floor_plan_and_elevations.png"},{"u":"https://danam.cats.uni-heidelberg.de/files/uploadedfiles/SUN0200-003_P_20191104_01.JPG","o":"NHDP","l":"CC BY-SA 4.0 (NHDP)","p":"https://danam.cats.uni-heidelberg.de/files/uploadedfiles/SUN0200-003_P_20191104_01.JPG"},{"u":"https://danam.cats.uni-heidelberg.de/files/uploadedfiles/SUN0200-002_P_20191104_01.jpg","o":"NHDP","l":"CC BY-SA 4.0 (NHDP)","p":"https://danam.cats.uni-heidelberg.de/files/uploadedfiles/SUN0200-002_P_20191104_01.jpg"},{"u":"https://danam.cats.uni-heidelberg.de/files/uploadedfiles/SUN0200-001_P_20191017_01.jpg","o":"NHDP","l":"CC BY-SA 4.0 (NHDP)","p":"https://danam.cats.uni-heidelberg.de/files/uploadedfiles/SUN0200-001_P_20191017_01.jpg"}],"c4:Mati B\u0101h\u0101c\u0101 (1863 CE) [786375ae]":[{"u":"https://danam.cats.uni-heidelberg.de/files/uploadedfiles/LAL0891_P_20181106_09_fUFLjpy.jpg","o":"NHDP","l":"CC BY-SA 4.0 (NHDP)","p":"https://danam.cats.uni-heidelberg.de/files/uploadedfiles/LAL0891_P_20181106_09_fUFLjpy.jpg"},{"u":"https://danam.cats.uni-heidelberg.de/files/uploadedfiles/LAL0891_I_20181106_03_OcH2rE4.jpg","o":"NHDP","l":"CC BY-SA 4.0 (NHDP)","p":"https://danam.cats.uni-heidelberg.de/files/uploadedfiles/LAL0891_I_20181106_03_OcH2rE4.jpg"},{"u":"https://danam.cats.uni-heidelberg.de/files/uploadedfiles/LAL0891_I_20181106_01_bO83vnZ.jpg","o":"NHDP","l":"CC BY-SA 4.0 (NHDP)","p":"https://danam.cats.uni-heidelberg.de/files/uploadedfiles/LAL0891_I_20181106_01_bO83vnZ.jpg"},{"u":"https://danam.cats.uni-heidelberg.de/files/uploadedfiles/LAL0891_I_20181106_02.jpg","o":"NHDP","l":"CC BY-SA 4.0 (NHDP)","p":"https://danam.cats.uni-heidelberg.de/files/uploadedfiles/LAL0891_I_20181106_02.jpg"},{"u":"https://danam.cats.uni-heidelberg.de/files/uploadedfiles/LAL0891_P_20181106_07_Omnr4GB.jpg","o":"NHDP","l":"CC BY-SA 4.0 (NHDP)","p":"https://danam.cats.uni-heidelberg.de/files/uploadedfiles/LAL0891_P_20181106_07_Omnr4GB.jpg"},{"u":"https://danam.cats.uni-heidelberg.de/files/uploadedfiles/LAL0891_P_20181106_08.jpg","o":"NHDP","l":"CC BY-SA 4.0 (NHDP)","p":"https://danam.cats.uni-heidelberg.de/files/uploadedfiles/LAL0891_P_20181106_08.jpg"}],"c4:nm:1536 church monuments":["https://commons.wikimedia.org/wiki/Special:FilePath/Tarn%C3%B3w_katedra_nagrobek.jpg"],"c4:nm:1761 church monuments":["https://commons.wikimedia.org/wiki/Special:FilePath/Tombstone_of_J%C3%B3zefina_Sobieska.jpg"],"c4:nm:sagarmatha choudhary eye hospital":["https://commons.wikimedia.org/wiki/Special:FilePath/2010-10-03-quadriga-by-RalfR-095.jpg","https://commons.wikimedia.org/wiki/Special:FilePath/2010-10-03-quadriga-by-RalfR-096.jpg","https://commons.wikimedia.org/wiki/Special:FilePath/2010-10-03-quadriga-by-RalfR-121.jpg","https://commons.wikimedia.org/wiki/Special:FilePath/2010-10-03-quadriga-by-RalfR-122.jpg"],"c4:geo:27.7212,85.3623":["https://commons.wikimedia.org/wiki/Special:FilePath/20110725_Budha_eyes_closeup_Bodhnath_Stupa_Kathmandu_Nepal.jpg"],"c4:geo:27.7195,85.3572":["https://commons.wikimedia.org/wiki/Special:FilePath/Boudhanath_Stupa%2C_Kathmandu_Nepal.jpg"],"c4:geo:27.7219,85.3621":["https://commons.wikimedia.org/wiki/Special:FilePath/Buildings_around_Boudhanath_%2817642728428%29.jpg"],"c4:geo:27.7172,85.324":["https://commons.wikimedia.org/wiki/Special:FilePath/Monkey_Atop_Swaymbhu_%28222385643%29.jpeg"],"c4:geo:27.7136,85.2956":["https://commons.wikimedia.org/wiki/Special:FilePath/Monkey_atop_Swayambhu_%2812654016324%29.jpg"],"c4:geo:27.7214,85.3619":["https://commons.wikimedia.org/wiki/Special:FilePath/Nepal_2018-03-24_%2826807494517%29.jpg","https://commons.wikimedia.org/wiki/Special:FilePath/Nepal_2018-03-24_%2827806402868%29.jpg","https://commons.wikimedia.org/wiki/Special:FilePath/Nepal_2018-03-24_%2839844029730%29.jpg","https://commons.wikimedia.org/wiki/Special:FilePath/Nepal_2018-03-24_%2841674594291%29.jpg"],"c4:geo:27.715,85.2909":["https://commons.wikimedia.org/wiki/Special:FilePath/Nepal_2018-04-07_%2827413212177%29.jpg","https://commons.wikimedia.org/wiki/Special:FilePath/Nepal_2018-04-07_%2840477064630%29.jpg","https://commons.wikimedia.org/wiki/Special:FilePath/Nepal_2018-04-07_%2841358204265%29.jpg","https://commons.wikimedia.org/wiki/Special:FilePath/Nepal_2018-04-07_%2841549819954%29.jpg","https://commons.wikimedia.org/wiki/Special:FilePath/Nepal_2018-04-07_%2842260192061%29.jpg","https://commons.wikimedia.org/wiki/Special:FilePath/Nepal_2018-04-07_%2842260192761%29.jpg"],"c4:geo:27.6974,85.3315":["https://commons.wikimedia.org/wiki/Special:FilePath/Swayambhunath%2C_Monkeys_on_Stupas_%285202521010%29.jpg"],"c4:nm:golden temple, patan":["https://commons.wikimedia.org/wiki/Special:FilePath/Yawning_cat_%2846259264265%29.jpg"],"c4:Namobuddha stupa":["https://commons.wikimedia.org/wiki/Special:FilePath/Namobuddha_inside.jpg"],"c4:Indreshwar Temple, Panauti (details)":["https://commons.wikimedia.org/wiki/Special:FilePath/Bisheshor_Mahadev_temple_and_guard_of_Indreshwor.jpg","https://commons.wikimedia.org/wiki/Special:FilePath/Door_of_Indreshwor_mahadev.jpg","https://commons.wikimedia.org/wiki/Special:FilePath/Guard_of_Indreshwor_mahadev.jpg","https://commons.wikimedia.org/wiki/Special:FilePath/Indreswor_Temple_Panauti_IMG_1121_16.jpg","https://commons.wikimedia.org/wiki/Special:FilePath/Indreswor_Temple_Panauti_IMG_1121_17.jpg","https://commons.wikimedia.org/wiki/Special:FilePath/Monument_114155.jpg","https://commons.wikimedia.org/wiki/Special:FilePath/Monument_114203.jpg","https://commons.wikimedia.org/wiki/Special:FilePath/Monument_114216.jpg","https://commons.wikimedia.org/wiki/Special:FilePath/Monument_114223.jpg","https://commons.wikimedia.org/wiki/Special:FilePath/Monument_114233.jpg","https://commons.wikimedia.org/wiki/Special:FilePath/Monument_114244.jpg","https://commons.wikimedia.org/wiki/Special:FilePath/Monument_114259.jpg","https://commons.wikimedia.org/wiki/Special:FilePath/Monument_114312.jpg","https://commons.wikimedia.org/wiki/Special:FilePath/Monument_114319.jpg","https://commons.wikimedia.org/wiki/Special:FilePath/Monument_114338.jpg","https://commons.wikimedia.org/wiki/Special:FilePath/Monument_114347.jpg","https://commons.wikimedia.org/wiki/Special:FilePath/Monument_114359.jpg","https://commons.wikimedia.org/wiki/Special:FilePath/Monument_114416.jpg","https://commons.wikimedia.org/wiki/Special:FilePath/Monument_114424.jpg","https://commons.wikimedia.org/wiki/Special:FilePath/Monument_114432.jpg","https://commons.wikimedia.org/wiki/Special:FilePath/Monument_114730.jpg","https://commons.wikimedia.org/wiki/Special:FilePath/Monument_114733.jpg","https://commons.wikimedia.org/wiki/Special:FilePath/Monument_114737.jpg","https://commons.wikimedia.org/wiki/Special:FilePath/Monument_114741.jpg","https://commons.wikimedia.org/wiki/Special:FilePath/Monument_114745.jpg","https://commons.wikimedia.org/wiki/Special:FilePath/Monument_114748.jpg","https://commons.wikimedia.org/wiki/Special:FilePath/Monument_114803.jpg","https://commons.wikimedia.org/wiki/Special:FilePath/Monument_114908.jpg","https://commons.wikimedia.org/wiki/Special:FilePath/Monument_114916.jpg","https://commons.wikimedia.org/wiki/Special:FilePath/Monument_114944.jpg","https://commons.wikimedia.org/wiki/Special:FilePath/Monument_114958.jpg","https://commons.wikimedia.org/wiki/Special:FilePath/Monument_115003.jpg","https://commons.wikimedia.org/wiki/Special:FilePath/Monument_115013.jpg","https://commons.wikimedia.org/wiki/Special:FilePath/Monument_115017.jpg","https://commons.wikimedia.org/wiki/Special:FilePath/Monument_115024.jpg","https://commons.wikimedia.org/wiki/Special:FilePath/Monument_115039.jpg","https://commons.wikimedia.org/wiki/Special:FilePath/Monument_115046.jpg","https://commons.wikimedia.org/wiki/Special:FilePath/Monument_20180918_113911.jpg","https://commons.wikimedia.org/wiki/Special:FilePath/Monument_20180918_113919.jpg","https://commons.wikimedia.org/wiki/Special:FilePath/Monument_20180918_113927.jpg","https://commons.wikimedia.org/wiki/Special:FilePath/Monument_20180918_113938.jpg","https://commons.wikimedia.org/wiki/Special:FilePath/Monument_20180918_113946.jpg","https://commons.wikimedia.org/wiki/Special:FilePath/Monument_20180918_113954.jpg","https://commons.wikimedia.org/wiki/Special:FilePath/Monument_20180918_114007.jpg","https://commons.wikimedia.org/wiki/Special:FilePath/Monument_20180918_114017.jpg","https://commons.wikimedia.org/wiki/Special:FilePath/Monument_20180918_114025.jpg","https://commons.wikimedia.org/wiki/Special:FilePath/Monument_20180918_114037.jpg","https://commons.wikimedia.org/wiki/Special:FilePath/Monument_20180918_114055.jpg","https://commons.wikimedia.org/wiki/Special:FilePath/Monument_20180918_114105.jpg","https://commons.wikimedia.org/wiki/Special:FilePath/Monument_20180918_114130.jpg","https://commons.wikimedia.org/wiki/Special:FilePath/Monument_20180918_114145.jpg","https://commons.wikimedia.org/wiki/Special:FilePath/Monument_20180918_114328.jpg","https://commons.wikimedia.org/wiki/Special:FilePath/Panauti_Area_2017_128.jpg","https://commons.wikimedia.org/wiki/Special:FilePath/Panauti_Temple_Premises_1021_01.jpg","https://commons.wikimedia.org/wiki/Special:FilePath/Panauti_Temple_Premises_1021_02.jpg","https://commons.wikimedia.org/wiki/Special:FilePath/Panautitemple.jpg","https://commons.wikimedia.org/wiki/Special:FilePath/ShachiTirtha_Tribenighat_Panauti-IMG_4278.jpg","https://commons.wikimedia.org/wiki/Special:FilePath/ShachiTirtha_Tribenighat_Panauti-IMG_4324.jpg","https://commons.wikimedia.org/wiki/Special:FilePath/ShachiTirtha_Tribenighat_Panauti-IMG_4325.jpg","https://commons.wikimedia.org/wiki/Special:FilePath/ShachiTirtha_Tribenighat_Panauti-IMG_4326.jpg"],"c4:Indreshwar Temple, Panauti (gate)":["https://commons.wikimedia.org/wiki/Special:FilePath/Eastern_door_of_Indreshwor_mahadev.jpg","https://commons.wikimedia.org/wiki/Special:FilePath/Gateway_to_indreshwor_mahadev.jpg","https://commons.wikimedia.org/wiki/Special:FilePath/Indreshwor_Mahadev_II_DSC_7549.jpg","https://commons.wikimedia.org/wiki/Special:FilePath/Panauti_Temple_Premises_1011_38.jpg","https://commons.wikimedia.org/wiki/Special:FilePath/Panauti_Temple_Premises_1011_39.jpg","https://commons.wikimedia.org/wiki/Special:FilePath/Panauti_Temple_Premises_1011_40.jpg","https://commons.wikimedia.org/wiki/Special:FilePath/ShachiTirtha_Tribenighat_Panauti-IMG_4319.jpg","https://commons.wikimedia.org/wiki/Special:FilePath/ShachiTirtha_Tribenighat_Panauti-IMG_4320.jpg","https://commons.wikimedia.org/wiki/Special:FilePath/ShachiTirtha_Tribenighat_Panauti-IMG_4322.jpg"],"c4:Indreshwar Temple, Panauti (Nandi)":["https://commons.wikimedia.org/wiki/Special:FilePath/Bull_in_front_of_indreshwor_mahadev.jpg","https://commons.wikimedia.org/wiki/Special:FilePath/Garud_of_indreshwori.jpg","https://commons.wikimedia.org/wiki/Special:FilePath/Guards_of_Lord_Mahadev_temple.jpg","https://commons.wikimedia.org/wiki/Special:FilePath/Panauti_Temple_Premises_1021_17.jpg","https://commons.wikimedia.org/wiki/Special:FilePath/Panauti_Temple_Premises_1021_18.jpg","https://commons.wikimedia.org/wiki/Special:FilePath/Panauti_Temple_Premises_1021_19.jpg","https://commons.wikimedia.org/wiki/Special:FilePath/Panauti_Temple_Premises_1021_20.jpg","https://commons.wikimedia.org/wiki/Special:FilePath/Panauti_Temple_Premises_1021_21.jpg","https://commons.wikimedia.org/wiki/Special:FilePath/ShachiTirtha_Tribenighat_Panauti-IMG_4408.jpg","https://commons.wikimedia.org/wiki/Special:FilePath/Statue_of_bull_in_front_of_Mahadev_temple.jpg"],"c4:Namobuddha monastery":["https://commons.wikimedia.org/wiki/Special:FilePath/Namobuddha_inside.jpg"],"c4:Santaneshwor Mahadev Temple, Jharuwarasi (interior)":["https://commons.wikimedia.org/wiki/Special:FilePath/Below_Santaneswor_mahadev_01.jpg","https://commons.wikimedia.org/wiki/Special:FilePath/Below_Santaneswor_mahadev_02.jpg","https://commons.wikimedia.org/wiki/Special:FilePath/Inside_View_of_Santaneswor_Mahadev_02.jpg","https://commons.wikimedia.org/wiki/Special:FilePath/Inside_View_of_Santaneswor_Mahadev_03.jpg","https://commons.wikimedia.org/wiki/Special:FilePath/Inside_View_of_Santaneswor_Mahadev_04.jpg","https://commons.wikimedia.org/wiki/Special:FilePath/Inside_View_of_Santaneswor_Mahadev_05.jpg","https://commons.wikimedia.org/wiki/Special:FilePath/Inside_View_of_Santaneswor_Mahadev_06.jpg","https://commons.wikimedia.org/wiki/Special:FilePath/Inside_View_of_Santaneswor_Mahadev_07.jpg","https://commons.wikimedia.org/wiki/Special:FilePath/Inside_View_of_Santaneswor_Mahadev_08.jpg","https://commons.wikimedia.org/wiki/Special:FilePath/Inside_View_of_Santaneswor_Mahadev_09.jpg","https://commons.wikimedia.org/wiki/Special:FilePath/Inside_View_of_Santaneswor_Mahadev_10.jpg","https://commons.wikimedia.org/wiki/Special:FilePath/Inside_View_of_Santaneswor_Mahadev_11.jpg","https://commons.wikimedia.org/wiki/Special:FilePath/Inside_View_of_Santaneswor_Mahadev_12.jpg","https://commons.wikimedia.org/wiki/Special:FilePath/Inside_View_of_Santaneswor_Mahadev_13.jpg","https://commons.wikimedia.org/wiki/Special:FilePath/Inside_View_of_Santaneswor_Mahadev_14.jpg","https://commons.wikimedia.org/wiki/Special:FilePath/Inside_View_of_Santaneswor_Mahadev_15.jpg","https://commons.wikimedia.org/wiki/Special:FilePath/Inside_View_of_Santaneswor_Mahadev_16.jpg","https://commons.wikimedia.org/wiki/Special:FilePath/Inside_View_of_Santaneswor_Mahadev_19.jpg","https://commons.wikimedia.org/wiki/Special:FilePath/Inside_View_of_Santaneswor_Mahadev_20.jpg","https://commons.wikimedia.org/wiki/Special:FilePath/Inside_View_of_Santaneswor_Mahadev_21.jpg","https://commons.wikimedia.org/wiki/Special:FilePath/Santaneswor_Mahadev_01.jpg","https://commons.wikimedia.org/wiki/Special:FilePath/Shree_Santaneshwor_Mahadev_Temple_20180828_152034.jpg","https://commons.wikimedia.org/wiki/Special:FilePath/Shree_Santaneshwor_Mahadev_Temple_20180828_152036.jpg","https://commons.wikimedia.org/wiki/Special:FilePath/Shree_Santaneshwor_Mahadev_Temple_20180828_152039.jpg","https://commons.wikimedia.org/wiki/Special:FilePath/Shree_Santaneshwor_Mahadev_Temple_20180828_152113.jpg","https://commons.wikimedia.org/wiki/Special:FilePath/Shree_Santaneshwor_Mahadev_Temple_20180828_152121.jpg","https://commons.wikimedia.org/wiki/Special:FilePath/Shree_Santaneshwor_Mahadev_Temple_20180828_152125.jpg"],"c4:Choede monastery (Lo Manthang)":["https://commons.wikimedia.org/wiki/Special:FilePath/Mustang-Lo_Manthang-20-Choede_Lhakhang-Innenhof-gje.jpg"],"c4:Naxal Bhagawati Temple":["https://commons.wikimedia.org/wiki/Special:FilePath/Statue_of_Bhagwati_inside_Naksaal_Bhagwati_Temple_01.jpg","https://commons.wikimedia.org/wiki/Special:FilePath/Statue_of_Bhagwati_inside_Naksaal_Bhagwati_Temple_02.jpg","https://commons.wikimedia.org/wiki/Special:FilePath/Statue_of_Bhagwati_inside_Naksaal_Bhagwati_Temple_03.jpg","https://commons.wikimedia.org/wiki/Special:FilePath/Statue_of_Bhagwati_inside_Naksaal_Bhagwati_Temple_04.jpg","https://commons.wikimedia.org/wiki/Special:FilePath/Statue_of_Bhagwati_inside_Naksaal_Bhagwati_Temple_05.jpg","https://commons.wikimedia.org/wiki/Special:FilePath/Tympanum_of_Bhagwati_Temple_Naksaal%2C_Kathmandu.jpg","https://commons.wikimedia.org/wiki/Special:FilePath/Tympanum_of_Naksaal_Bhagwati_Temple_07.jpg"],"c4:geo:26.731,85.925":["https://commons.wikimedia.org/wiki/Special:FilePath/Inside_view_of_Vivah_Mandap%2C_Janakpur-September_22%2C_2016-IMG_7385.jpg"]}